smart_letters/__init__.py
smart_letters/cache.py
smart_letters/config.py
smart_letters/exceptions.py
smart_letters/format.py
smart_letters/generate.py
smart_letters/logging.py
smart_letters/main.py
smart_letters/prompt.py
smart_letters/render.py
smart_letters/schemas.py
smart_letters/utilities.py
smart_letters/version.py
smart_letters/assets/FiraSans-Bold.ttf
smart_letters/assets/FiraSans-Regular.ttf
smart_letters/assets/NotoEmoji-Regular.ttf
smart_letters/assets/dev_prompt.txt
smart_letters/assets/fake.txt
smart_letters/assets/styles.css
smart_letters/assets/user_prompt.txt.mako
smart_letters-0.3.0.dist-info/METADATA
smart_letters-0.3.0.dist-info/WHEEL
smart_letters-0.3.0.dist-info/entry_points.txt
smart_letters-0.3.0.dist-info/licenses/LICENSE.md
smart_letters-0.3.0.dist-info/RECORD
