Metadata-Version: 2.4
Name: smart-letters
Version: 0.3.0
Summary: Generate cover letters for specific job postings using OpenAI.
Project-URL: homepage, https://github.com/dusktreader/smart-letters
Project-URL: source, https://github.com/dusktreader/smart-letters
Project-URL: changelog, https://github.com/dusktreader/smart-letters/blob/main/CHANGELOG.md
Author-email: Tucker Beck <tucker.beck@gmail.com>
License-File: LICENSE.md
Requires-Python: >=3.13
Requires-Dist: httpx>=0.28.1
Requires-Dist: inflection>=0.5.1
Requires-Dist: loguru>=0.7.3
Requires-Dist: mako>=1.3.9
Requires-Dist: markdown>=3.7
Requires-Dist: openai>=1.65.1
Requires-Dist: py-buzz>=5.0.2
Requires-Dist: pydantic>=2.10.6
Requires-Dist: pyperclip>=1.9.0
Requires-Dist: snick>=1.4.1
Requires-Dist: typer>=0.15.2
Requires-Dist: weasyprint>=64.1
